txtagt.py
txtagt-0.0.1.dist-info/METADATA
txtagt-0.0.1.dist-info/WHEEL
txtagt-0.0.1.dist-info/RECORD
