Metadata-Version: 2.1
Name: txtagt
Version: 0.0.1
Summary: a txt agent
Home-page: https://ragt.ag/code/txtagt
License: BSD-2-Clause
Author: Angelo Gladding
Author-email: angelo@ragt.ag
Requires-Python: >=3.10,<3.11
Classifier: License :: OSI Approved :: BSD License
Classifier: Programming Language :: Python :: 3
Classifier: Programming Language :: Python :: 3.10
